v3.0/fifo_null_pages.sv
module fifo_null_pages
(
    input clk,
    input rst_n,

    input pop_head,
    output reg [10:0] head_addr,

    input push_tail,
    input [10:0] tail_addr
);

reg [10:0] fifo [2047:0];
reg [10:0] head_ptr = 1;
reg [10:0] tail_ptr = 0;
reg initialized = 1;

always @(posedge clk or negedge rst_n) begin
    if(!rst_n) begin
        head_ptr <= 1;
        tail_ptr <= 0;
        head_addr <= 0;
        fifo[0] <= 0;
        initialized <= 1;
    end else begin
        if(pop_head) 
            if(initialized && head_addr < 2047) 
                head_addr <= head_addr + 1;
            else begin
                initialized <= 0;
                head_ptr <= head_ptr + 1;
                head_addr <= fifo[head_ptr + 1];
            end
        if(push_tail) begin
            fifo[tail_ptr + 1] <= tail_addr;
            tail_ptr <= tail_ptr + 1;
        end
    end
end

endmodule

v3.0/tb_fifo_null_pages.v
//~ `New testbench
`timescale  1ns / 1ps
`include "./v3.0/fifo_null_pages.sv"

module tb_fifo_null_pages();

    reg clk = 1;
    reg rst_n = 1;

    reg pop_head = 0;
    wire [10:0] head_addr;

    reg push_tail = 0;
    reg [10:0] tail_addr = 0;

    // mux Parameters
    parameter PERIOD  = 10;

    initial
    begin
        forever
        #(PERIOD/2)  clk=~clk;
    end

    fifo_null_pages fifo(
        .clk(clk),
        .rst_n(rst_n),
        .pop_head(pop_head),
        .head_addr(head_addr),
        .push_tail(push_tail),
        .tail_addr(tail_addr)
    );

    initial
    begin
        $dumpfile("test_fifo_null_pages.vcd");
        $dumpvars();
        #10
        rst_n = 0;
        #10 
        rst_n = 1;
        #10 
        pop_head = 1;
        #10
        #10
        #10
        #10
        #10
        #10
        pop_head = 0;
        push_tail = 1;
        tail_addr = 11'd0;
        #10
        tail_addr = 11'd1;
        #10
        tail_addr = 11'd2;
        #10
        tail_addr = 11'd3;
        #10
        $finish;
    end

endmodule

v3.0/test_fifo_null_pages.vcd
$date
	Wed May 01 14:30:56 2024
$end
$version
	Icarus Verilog
$end
$timescale
	1ps
$end
$scope module tb_fifo_null_pages $end
$var wire 11 ! head_addr [10:0] $end
$var parameter 32 " PERIOD $end
$var reg 1 # clk $end
$var reg 1 $ pop_head $end
$var reg 1 % push_tail $end
$var reg 1 & rst_n $end
$var reg 11 ' tail_addr [10:0] $end
$scope module fifo $end
$var wire 1 # clk $end
$var wire 1 $ pop_head $end
$var wire 1 % push_tail $end
$var wire 1 & rst_n $end
$var wire 11 ( tail_addr [10:0] $end
$var reg 11 ) head_addr [10:0] $end
$var reg 11 * head_ptr [10:0] $end
$var reg 1 + initialized $end
$var reg 11 , tail_ptr [10:0] $end
$upscope $end
$upscope $end
$enddefinitions $end
$comment Show the parameter values. $end
$dumpall
b1010 "
$end
#0
$dumpvars
b0 ,
1+
b1 *
bx )
b0 (
b0 '
1&
0%
0$
1#
bx !
$end
#5000
0#
#10000
b0 !
b0 )
1#
0&
#15000
0#
#20000
1#
1&
#25000
0#
#30000
b1 !
b1 )
1#
1$
#35000
0#
#40000
b10 !
b10 )
1#
#45000
0#
#50000
b11 !
b11 )
1#
#55000
0#
#60000
b100 !
b100 )
1#
#65000
0#
#70000
b101 !
b101 )
1#
#75000
0#
#80000
b110 !
b110 )
1#
#85000
0#
#90000
b1 ,
1#
1%
0$
#95000
0#
#100000
b10 ,
1#
b1 '
b1 (
#105000
0#
#110000
b11 ,
1#
b10 '
b10 (
#115000
0#
#120000
b100 ,
1#
b11 '
b11 (
#125000
0#
#130000
b101 ,
1#
