v2.0/fifo_null_pages.sv
module fifo_null_pages
(
    input clk,
    input rst_n,

    input pop_head,
    output reg [10:0] head_addr,

    input push_tail,
    input [10:0] tail_addr
);

reg [15:0] buf_mem [255:0];
reg [7:0] head_ptr = 0;
reg [7:0] tail_ptr = 63;

reg [15:0] head;
reg [15:0] tail;

integer i;

always @(posedge clk or negedge rst_n) begin
    if(!rst_n) begin
        for(i = 0; i < 64; i = i + 1) 
            buf_mem[i] <= {i<<5,5'd31};
        for(i = 64; i < 256; i = i + 1) 
            buf_mem[i] <= 0;
    end
    else begin
        if(push_tail) begin
            tail = buf_mem[tail_ptr];
            if(tail[15:5] + tail[4:0] == tail_addr - 1 && tail[4:0] < 31)
                tail = tail + 1;
            else begin
                tail_ptr = tail_ptr + 1;
                tail = {tail_addr, 5'b0};
            end
            buf_mem[tail_ptr] = tail;
        end

        head = buf_mem[head_ptr];
        head_addr = head[15:5];
        if(pop_head) begin
            if(head[4:0] == 0) begin
                head_ptr = head_ptr + 1;
                head = buf_mem[head_ptr];
            end
            else begin
                head = head + 5'b11111;
                buf_mem[head_ptr] = head;
            end
        end
    end
end

endmodule

v2.0/tb_fifo_null_pages.v
//~ `New testbench
`timescale  1ns / 1ps
`include "fifo_null_pages.sv"

module tb_fifo_null_pages();

    reg clk = 1;
    reg rst_n = 1;

    reg pop_head = 0;
    wire [10:0] head_addr;

    reg push_tail = 0;
    reg [10:0] tail_addr = 0;

    // mux Parameters
    parameter PERIOD  = 10;

    initial
    begin
        forever
        #(PERIOD/2)  clk=~clk;
    end

    fifo_null_pages fifo(
        .clk(clk),
        .rst_n(rst_n),
        .pop_head(pop_head),
        .head_addr(head_addr),
        .push_tail(push_tail),
        .tail_addr(tail_addr)
    );

    initial
    begin
        $dumpfile("test_fifo_null_pages.vcd");
        $dumpvars();
        #10
        rst_n = 0;
        #10 
        rst_n = 1;
        #10 
        pop_head = 1;
        #10
        #10
        #10
        #10
        #10
        #10
        pop_head = 0;
        push_tail = 1;
        tail_addr = 11'd0;
        #10
        tail_addr = 11'd1;
        #10
        tail_addr = 11'd2;
        #10
        tail_addr = 11'd3;
        #10
        $finish;
    end

endmodule

v2.0/test_fifo_null_pages.vcd
$date
	Sun Apr 14 01:55:52 2024
$end
$version
	Icarus Verilog
$end
$timescale
	1ps
$end
$scope module tb_fifo_null_pages $end
$var wire 11 ! head_addr [10:0] $end
$var parameter 32 " PERIOD $end
$var reg 1 # clk $end
$var reg 1 $ pop_head $end
$var reg 1 % push_tail $end
$var reg 1 & rst_n $end
$var reg 11 ' tail_addr [10:0] $end
$scope module fifo $end
$var wire 1 # clk $end
$var wire 1 $ pop_head $end
$var wire 1 % push_tail $end
$var wire 1 & rst_n $end
$var wire 11 ( tail_addr [10:0] $end
$var reg 16 ) head [15:0] $end
$var reg 11 * head_addr [10:0] $end
$var reg 8 + head_ptr [7:0] $end
$var reg 16 , tail [15:0] $end
$var reg 8 - tail_ptr [7:0] $end
$var integer 32 . i [31:0] $end
$upscope $end
$upscope $end
$enddefinitions $end
$comment Show the parameter values. $end
$dumpall
b1010 "
$end
#0
$dumpvars
bx .
bx -
bx ,
bx +
bx *
bx )
b0 (
b0 '
1&
0%
0$
1#
bx !
$end
#5000
0#
#10000
b111111 -
b0 +
b100000000 .
1#
0&
#15000
0#
#20000
b0 !
b0 *
b11111 )
1#
1&
#25000
0#
#30000
b111110 )
1#
1$
#35000
0#
#40000
b1011101 )
b1 !
b1 *
1#
#45000
0#
#50000
b1111100 )
b10 !
b10 *
1#
#55000
0#
#60000
b10011011 )
b11 !
b11 *
1#
#65000
0#
#70000
b10111010 )
b100 !
b100 *
1#
#75000
0#
#80000
b11011001 )
b101 !
b101 *
1#
#85000
0#
#90000
b110 !
b110 *
b1000000 -
b0 ,
1#
1%
0$
#95000
0#
#100000
b1 ,
1#
b1 '
b1 (
#105000
0#
#110000
b10 ,
1#
b10 '
b10 (
#115000
0#
#120000
b11 ,
1#
b11 '
b11 (
#125000
0#
#130000
b1100000 ,
b1000001 -
1#
